AUTHORS.rst
LICENSE
README.md
autoflake8/__init__.py
autoflake8/cli.py
autoflake8/fix.py
autoflake8/multiline.py
autoflake8/pending_fix.py
autoflake8-0.4.1.dist-info/LICENSE
autoflake8-0.4.1.dist-info/METADATA
autoflake8-0.4.1.dist-info/WHEEL
autoflake8-0.4.1.dist-info/entry_points.txt
autoflake8-0.4.1.dist-info/RECORD
